{
  "options": {
    "original_lang": "Dutch",
    "translated_lang": "English"
  },
  "words": [
    {
	    "original": "doing homework",
	    "translation": "huiswerk maken"
    },
    {
	    "original": "playing football",
	    "translation": "voetballen"
    },
    {
	    "original": "studying",
	    "translation": "studeren"
    },
    {
	    "original": "reading",
	    "translation": "lezen"
    },
    {
	    "original": "dancing",
	    "translation": "dansen"
    },
    {
	    "original": "tidying up",
	    "translation": "opruimen"
    },
    {
	    "original": "singing",
	    "translation": "zingen"
    },
    {
	    "original": "doing housework",
	    "translation": "het huishouden doen"
    },
    {
	    "original": "riding a bike",
	    "translation": "fietsen"
    },
    {
	    "original": "hobby",
	    "translation": "hobby"
    },
    {
	    "original": "enjoy",
	    "translation": "genieten"
    },
    {
	    "original": "exercise",
	    "translation": "lichaamsbeweging"
    },
    {
	    "original": "puzzle",
	    "translation": "puzzel"
    },
    {
	    "original": "crossword",
	    "translation": "kruiswoordpuzzel"
    },
    {
	    "original": "play computer games",
	    "translation": "computerspelletjes spelen"
    },
    {
	    "original": "be in a club",
	    "translation": "op een club zitten"
    },
    {
	    "original": "play an instrument",
	    "translation": "een instrument bespelen"
    },
    {
	    "original": "collect things",
	    "translation": "dingen verzamelen"
    },
    {
	    "original": "write a blog",
	    "translation": "een blog schrijven"
    },
    {
	    "original": "take photographs",
	    "translation": "foto's nemen"
    },
    {
	    "original": "keep a pet",
	    "translation": "een huisdier hebben"
    },
    {
	    "original": "play the piano",
	    "translation": "pianospelen"
    },
    {
	    "original": "collect stamps",
	    "translation": "postzegels verzamelen"
    },
    {
	    "original": "play on-line games",
	    "translation": "online games spelen"
    },
    {
	    "original": "cooking",
	    "translation": "koken"
    },
    {
	    "original": "collect autographs",
	    "translation": "handtekeningen verzamelen"
    },
    {
	    "original": "write a poem",
	    "translation": "een gedicht schrijven"
    },
    {
	    "original": "always",
	    "translation": "altijd"
    },
    {
	    "original": "sometimes",
	    "translation": "soms"
    },
    {
	    "original": "never",
	    "translation": "nooit"
    },
    {
	    "original": "occasionally",
	    "translation": "af en toe"
    },
    {
	    "original": "often",
	    "translation": "vaak"
    },
    {
	    "original": "rarely",
	    "translation": "zelden"
    },
    {
	    "original": "usually",
	    "translation": "gewoonlijk"
    },
    {
	    "original": "every day",
	    "translation": "elke dag"
    },
    {
	    "original": "three times a week",
	    "translation": "drie keer per week"
    },
    {
	    "original": "once a month",
	    "translation": "een keer per maand"
    },
    {
	    "original": "make videos",
	    "translation": "video's maken"
    },
    {
	    "original": "have a problem",
	    "translation": "een probleem hebben"
    },
    {
	    "original": "have dinner",
	    "translation": "het avondeten gebruiken"
    },
    {
	    "original": "have fun",
	    "translation": "plezier hebben"
    },
    {
	    "original": "have a rest",
	    "translation": "een slaapje doen"
    },
    {
	    "original": "have a good time",
	    "translation": "het naar z'n zin hebben"
    },
    {
	    "original": "have a shower",
	    "translation": "douchen"
    },
    {
	    "original": "have time",
	    "translation": "tijd hebben"
    },
    {
	    "original": "have a hobby",
	    "translation": "een hobby hebben"
    },
    {
	    "original": "tidy",
	    "translation": "opgeruimd"
    },
    {
	    "original": "busy",
	    "translation": "druk"
    },
    {
	    "original": "relax",
	    "translation": "zich ontspannen"
    },
    {
	    "original": "definitely",
	    "translation": "beslist"
    },
    {
	    "original": "strange",
	    "translation": "vreemd"
    },
    {
	    "original": "smile",
	    "translation": "glimlachen"
    },
    {
	    "original": "positive",
	    "translation": "positief"
    },
    {
	    "original": "interests",
	    "translation": "interesses"
    },
    {
	    "original": "pass the time",
	    "translation": "de tijd doorkomen"
    },
    {
	    "original": "can't stand",
	    "translation": "iets niet uit kunnen staan"
    },
    {
	    "original": "cheap",
	    "translation": "goedkoop"
    },
    {
	    "original": "expensive",
	    "translation": "duur"
    },
    {
	    "original": "fantastic",
	    "translation": "fantastisch"
    },
    {
	    "original": "dream",
	    "translation": "dromen"
    },
    {
	    "original": "wear",
	    "translation": "dragen"
    },
    {
	    "original": "supermarket",
	    "translation": "supermarkt"
    },
    {
	    "original": "shopping",
	    "translation": "boodschappen doen"
    },
    {
	    "original": "colour",
	    "translation": "kleur"
    },
    {
	    "original": "cool",
	    "translation": "cool"
    },
    {
	    "original": "comfortable",
	    "translation": "comfortabel"
    },
    {
	    "original": "designer clothes",
	    "translation": "designerkleding"
    },
    {
	    "original": "clean",
	    "translation": "schoon"
    },
    {
	    "original": "bright",
	    "translation": "fel"
    },
    {
	    "original": "newsagent's",
	    "translation": "krantenwinkel"
    },
    {
	    "original": "chemist's",
	    "translation": "apotheek"
    },
    {
	    "original": "bookshop",
	    "translation": "boekwinkel"
    },
    {
	    "original": "clothes shop",
	    "translation": "kledingwinkel"
    },
    {
	    "original": "shoe shop",
	    "translation": "schoenwinkel"
    },
    {
	    "original": "department store",
	    "translation": "warenhuis"
    },
    {
	    "original": "post office",
	    "translation": "postkantoor"
    },
    {
	    "original": "taste",
	    "translation": "smaken"
    },
    {
	    "original": "smell",
	    "translation": "ruiken"
    },
    {
	    "original": "sound",
	    "translation": "klinken"
    },
    {
	    "original": "look",
	    "translation": "er uitzien"
    },
    {
	    "original": "customer",
	    "translation": "klant"
    },
    {
	    "original": "size",
	    "translation": "maat"
    },
    {
	    "original": "take",
	    "translation": "hebben"
    },
    {
	    "original": "try on",
	    "translation": "passen"
    },
    {
	    "original": "cost",
	    "translation": "kosten"
    },
    {
	    "original": "T-shirt",
	    "translation": "T-shirt"
    },
    {
	    "original": "jeans",
	    "translation": "jeans"
    },
    {
	    "original": "shorts",
	    "translation": "korte broek"
    },
    {
	    "original": "shoes",
	    "translation": "schoenen"
    },
    {
	    "original": "trousers",
	    "translation": "broek"
    },
    {
	    "original": "belt",
	    "translation": "riem"
    },
    {
	    "original": "boots",
	    "translation": "laarzen"
    },
    {
	    "original": "jacket",
	    "translation": "jasje"
    },
    {
	    "original": "trainers",
	    "translation": "gymschoenen"
    },
    {
	    "original": "shirt",
	    "translation": "overhemd"
    },
    {
	    "original": "dress",
	    "translation": "jurk"
    },
    {
	    "original": "jumper",
	    "translation": "trui"
    },
    {
	    "original": "spend",
	    "translation": "uitgeven"
    },
    {
	    "original": "shopping mall",
	    "translation": "(overdekt) winkelcentrum"
    },
    {
	    "original": "market",
	    "translation": "markt"
    },
    {
	    "original": "good-looking",
	    "translation": "knap"
    },
    {
	    "original": "interesting",
	    "translation": "interessant"
    },
    {
	    "original": "fascinating",
	    "translation": "boeiend"
    },
    {
	    "original": "exciting",
	    "translation": "spannend"
    },
    {
	    "original": "unusual",
	    "translation": "apart"
    },
    {
	    "original": "plan",
	    "translation": "plan"
    },
    {
	    "original": "terrible",
	    "translation": "afschuwelijk"
    },
    {
	    "original": "magazine",
	    "translation": "tijdschrift"
    },
    {
	    "original": "laugh at",
	    "translation": "uitlachen"
    },
    {
	    "original": "surprise",
	    "translation": "verrassen"
    },
    {
	    "original": "interested in",
	    "translation": "geïnteresseerd in"
    },
    {
	    "original": "popular",
	    "translation": "populair"
    },
    {
	    "original": "stall",
	    "translation": "kraam"
    },
    {
	    "original": "bargain",
	    "translation": "koopje"
    },
    {
	    "original": "open-air",
	    "translation": "openlucht"
    }
  ]
}
